{"children":[{"children":[],"uri":"https://www.notion.so/dc9af8f02b384d449ab5185fc72fe8ae","type":"text","createdTime":1611476400000,"lastEditedTime":1611476520000,"title":[["오랜만에 React Helmet을 쓰려고 세팅을 하는 와중에 문제가 아래와 같은 에러 문구가 출력되어 해결하기 위해 찾다보니 "],["깃헙 이슈",[["a","https://github.com/nfl/react-helmet/issues/548"]]],["에 남겨진 원인과 해결 방법을 발견하였다."]]},{"children":[],"uri":"https://www.notion.so/cd302d86f193476888e84cf8af9a9fde","type":"quote","createdTime":1611476558919,"lastEditedTime":1611476520000,"title":[["Warning: Using UNSAFE_componentWillMount in strict mode is not recommended and may indicate bugs in your code. See ",[["h","red"]]],["https://reactjs.org/link/unsafe-component-lifecycles",[["a","https://reactjs.org/link/unsafe-component-lifecycles"],["h","red"]]],[" for details.",[["h","red"]]]]},{"children":[],"uri":"https://www.notion.so/88528b8d06f04d8bad97114a815ee96d","type":"heading","createdTime":1611476520000,"lastEditedTime":1611476700000,"title":[["원인"]],"depth":3},{"children":[],"uri":"https://www.notion.so/8211f14ce32c445385f774cd9fe746a8","type":"text","createdTime":1611476700000,"lastEditedTime":1611476820000,"title":[["React 16이상 버젼 이상부터 Context API에 더 엄격한 조건이 추가 되면서, 현재 개발된 React Helmet v6에서 경고 문구가 출력되고 있다. 현재 수리 중이며 7 버젼에 이 이슈가 해결될 예정이라고 한다. "]]},{"children":[],"uri":"https://www.notion.so/901cfc234f3b40cfb9f719182fb281bd","type":"quote","createdTime":1611476800208,"lastEditedTime":1611476760000,"title":[["We're looking into Context API to remove our dependency on react-side-effect. Targeting for v7."]]},{"children":[],"uri":"https://www.notion.so/f9a41b2c5ec4449aaf87957b1e19f911","type":"heading","createdTime":1611476700000,"lastEditedTime":1611476820000,"title":[["임시방편"]],"depth":3},{"children":[],"uri":"https://www.notion.so/c78467fe478d477cb2b23af6a50aa7d3","type":"text","createdTime":1611476820000,"lastEditedTime":1611477060000,"title":[["react-helmet-async",[["c",null],["a","https://www.npmjs.com/package/react-helmet-async"]]],["라는 라이브러리",[["a","https://www.npmjs.com/package/react-helmet-async"]]],["를 통해 "],["UNSAFE_componentWillMount",[["c",null]]],[" 이슈를 임시로 해결할 수 있다. 우선은 이 방법을 쓰고 나중에 v7으로 업데이트 하면서 관련 디펜던시를 수정하도록 하자."]]},{"children":[],"uri":"https://www.notion.so/677d5e9647994ca794d5baf8efb43073","type":"bookmark","createdTime":1611476940000,"lastEditedTime":1611476940000,"link":"https://open.nytimes.com/the-future-of-meta-tag-management-for-modern-react-development-ec26a7dc9183","title":"The Future of Meta Tag Management for Modern React Development","description":"Introducing React-Helmet-Async, an open-sourced project supported by The New York Times","icon":"https://miro.medium.com/fit/c/256/256/1*QUlYX1snC5csKT-E6Bmxvw.jpeg","cover":"https://miro.medium.com/max/1200/1*vDXgFfx0RKDrU_0yXJlP_g.jpeg"}],"uri":"https://www.notion.so/eb031c2f39094f50b11bcb017746b44a","type":"page","createdTime":1611476400000,"lastEditedTime":1611477060000,"title":[["React Helmet"]],"icon":"⛑️","fullWidth":false,"coverPosition":1,"properties":{"!`\"w":[["Yes"]],"'2]%":[["react-helmet-issue-with-react16"]],"98uZ":[["React 16과 React Helmet 사이의 충돌 해결 과정"]],":H`m":[["Yes"]],"xY$N":[["‣",[["d",{"type":"date","start_date":"2021-01-24"}]]]],"{iD?":[["react,library"]],"|Ay0":[["post"]],"title":[["React Helmet"]]}}